{"_id":{"$oid":"549b4e3aeabc883b30e72be9"},"title":"The RPG Academy","url":"http://therpgacademy.com/","level":"Affiliate","image":"png","random":0.8445026273839176,"sortName":"the rpg academy","networks":["rpga"],"categories":["Podcast"]}
{"_id":{"$oid":"553c4b68eabc883e172ece0a"},"title":"BattleBards","sortName":"battlebards","url":"https://www.kickstarter.com/projects/battlebards/battlebards-epic-fantasy-audio-for-tabletop-rpgs","level":"Affiliate","image":"jpg","random":0.10089784511364996,"networks":[],"categories":["Accessories"]}
{"_id":{"$oid":"553c4be4eabc8800192ece0a"},"title":"Sharkbone Podcast","sortName":"sharkbone podcast","url":"http://sharkbonepodcast.com/","level":"Affiliate","random":0.6962287242058665,"image":"png","networks":["rpga"],"categories":["Podcast"]}
{"_id":{"$oid":"553c4c55eabc88ff182ece0a"},"title":"Melvin Smif's Geekery","sortName":"melvin smif's geekery","url":"https://melsmifgames.wordpress.com/","level":"Affiliate","random":0.925032903207466,"networks":["rpga"],"categories":["Blog"],"image":"jpg"}
{"_id":{"$oid":"553c4c5feabc880f192ece0a"},"title":"RPG Gamer Dad","sortName":"rpg gamer dad","url":"https://rpggamerdad.wordpress.com/","level":"Affiliate","random":0.5369461444206536,"image":"jpg","networks":["rpga"],"categories":["Podcast"],"flags":[]}
{"_id":{"$oid":"553c6632eabc88051b2ece0a"},"title":"Delve","sortName":"delve","url":"http://www.madadventurers.com/category/field-recordings/delve/","level":"Link","networks":[],"categories":["Podcast"],"random":0.42738392134197056,"image":"jpg"}
{"_id":{"$oid":"553c6824eabc88321b2ece0a"},"title":"Stories of the Fifth Age","sortName":"stories of the fifth age","url":"http://www.madadventurers.com/category/field-recordings/stories-of-the-fifth-age/","level":"Link","networks":[],"categories":["Podcast"],"random":0.553087770473212,"image":"png"}
{"_id":{"$oid":"553c792beabc88951c2ece0a"},"title":"Tales From the Hydian Way","sortName":"tales from the hydian way","url":"http://www.madadventurers.com/category/field-recordings/tales-from-the-hydian-way/","level":"Link","image":"png","networks":[],"categories":["Podcast"],"random":0.5891897417604923}
{"_id":{"$oid":"553cfb60eabc88b8242ece0a"},"title":"Some Guys and a Filthy Mage","sortName":"some guys and a filthy mage","url":"http://www.sgaafm.podbean.com/","level":"Link","image":"jpg","networks":[],"categories":["Podcast"],"random":0.836543918820098}
{"_id":{"$oid":"553d150beabc8891262ece0a"},"title":"FRPGCharacters.com","sortName":"frpgcharacters.com","url":"http://frpgcharacters.com/","level":"Link","networks":[],"categories":["Blog"],"random":0.9384969542734325}
{"_id":{"$oid":"553d3839eabc8846282ece0a"},"title":"AP Gaming","sortName":"ap gaming","url":"https://www.youtube.com/user/WVPOlarbear/featured","level":"Link","image":"jpg","networks":[],"categories":["Videocast","Liveplay"],"random":0.8743995353579521}
{"_id":{"$oid":"553d599deabc88d0292ece0a"},"title":"Firefly Podcast: Balls and Bayonets Brigade","sortName":"firefly podcast: balls and bayonets brigade","url":"https://itunes.apple.com/us/podcast/firefly-podcast-balls-bayonets/id966096665","level":"Link","image":"png","networks":[],"categories":["Podcast","Liveplay"],"random":0.29469656641595066}
{"_id":{"$oid":"553d8970eabc88ec2c2ece0a"},"title":"She's a Super Geek","sortName":"she's a super geek","url":"http://sasgeek.com/","level":"Link","image":"jpg","networks":["rpga"],"categories":["Podcast","Liveplay"],"random":0.6915074603166431}
{"_id":{"$oid":"553da46aeabc88942e2ece0a"},"title":"Gamerstable RPG Podcast","sortName":"gamerstable rpg podcast","url":"http://gamerstable.com/","level":"Link","image":"jpg","networks":[],"categories":["Podcast","Liveplay"],"random":0.25595728284679353}
{"_id":{"$oid":"553e20f2eabc881a33a16460"},"title":"3-Sided Die","sortName":"3-sided die","url":"http://www.3-sided-die.com/","level":"Link","image":"png","networks":[],"categories":["Blog"],"random":0.997245286591351}
{"_id":{"$oid":"554055ddeabc888c6fa16460"},"title":"RPGentlemen","sortName":"rpgentlemen","url":"http://rpgentlemen.com/","level":"Link","image":"jpg","networks":[],"categories":["Podcast","Liveplay"],"random":0.7430377376731485}
{"_id":{"$oid":"554055faeabc88936fa16460"},"title":"The Redacted Files","sortName":"the redacted files","url":"http://www.theredactedfiles.com/","level":"Link","image":"jpg","networks":[],"categories":["Podcast","Liveplay"],"random":0.3420383280608803}
{"_id":{"$oid":"554142f6eabc889b12a16460"},"title":"Gather 'Round the Table","sortName":"gather 'round the table","url":"http://gatherroundrpg.blogspot.com/","level":"Link","networks":[],"categories":["Blog"],"random":0.8163235764950514,"image":"png"}
{"_id":{"$oid":"554b7b6feabc88494763d3e0"},"title":"EldritchFire Press","sortName":"eldritchfire press","url":"http://www.efpress.net/","level":"Link","networks":[],"categories":["Blog"],"random":0.9751631785184145}
{"_id":{"$oid":"554d396beabc88a90563d3e0"},"title":"Dog Might","sortName":"dog might","url":"http://www.dogmight.com/","level":"Affiliate","networks":[],"categories":["Accessories"],"random":0.4456876909825951,"image":"jpg"}
{"_id":{"$oid":"55520c99eabc88912bfbdd9f"},"title":"Godsfall: A D\u0026D Podcast","sortName":"godsfall: a d\u0026d podcast","url":"http://www.godsfall.com/","level":"Link","image":"jpg","networks":[],"categories":["Podcast"],"random":0.06200449704192579}
{"_id":{"$oid":"5554b375eabc88e27ffbdd9f"},"title":"Dining Room Dungeon: Axes \u0026 Ales","sortName":"dining room dungeon: axes \u0026 ales","url":"http://drdpodcast.com/","level":"Link","image":"png","networks":[],"categories":["Podcast","Liveplay"],"flags":["content"],"random":0.874703997047618}
{"_id":{"$oid":"5554b3c6eabc888901fbdd9f"},"title":"Orcs Unlimited","sortName":"orcs unlimited","url":"http://orcsunlimited.com/","level":"Link","networks":[],"categories":["Dev"],"flags":[],"random":0.2532809474505484,"image":"jpg"}
{"_id":{"$oid":"555815d2eabc885377fbdd9f"},"title":"Rolecasters","sortName":"rolecasters","url":"http://www.rolecasters.net/","level":"Link","image":"jpg","networks":[],"categories":["Blog","Podcast"],"random":0.031776209361851215}
{"_id":{"$oid":"5558dfb4eabc88e50afbdda0"},"title":"Legends of Shadowfell","sortName":"legends of shadowfell","url":"http://www.legendsofshadowfall.com/","level":"Link","image":"png","networks":[],"categories":["Dev","Devs"],"random":0.16184864076785743}
{"_id":{"$oid":"5559d5d8eabc8814255ee8b1"},"title":"The Blue Heron Workshop","sortName":"the blue heron workshop","url":"http://www.blueheronworkshop.com/","level":"Link","image":"jpg","networks":[],"categories":["Accessories"],"random":0.9214525995776057}
{"_id":{"$oid":"555a107feabc88f02b5ee8b1"},"title":"The Arcology Podcast","sortName":"the arcology podcast","url":"http://arcologypodcast.com/","level":"Link","networks":[],"categories":["Podcast"],"random":0.574775411747396,"image":"jpg"}
{"_id":{"$oid":"555a95caeabc8821395ee8b1"},"title":"The Mad Adventurers Society","sortName":"the mad adventurers society","url":"http://www.madadventurers.com/","level":"Link","image":"png","networks":[],"categories":["Blog","Podcast","Liveplay"],"random":0.24704718287102878}
{"_id":{"$oid":"555bc1b3eabc88e6595ee8b1"},"title":"Gamer \u0026 Company","sortName":"gamer \u0026 company","url":"http://www.gamerandco.com/","level":"Link","image":"png","networks":[],"categories":["Podcast"],"random":0.3897555072326213}
{"_id":{"$oid":"55653cfeeabc880b2c0ad04e"},"title":"Space Tavern Game","sortName":"space tavern game","url":"http://spacetaverngames.com/","level":null,"image":"jpg","networks":[],"categories":["Blog","Videocast","Liveplay","Dev","Accessories"],"random":0.15364456735551357}
{"_id":{"$oid":"5565fa5beabc8842470ad04e"},"title":"Game Master's Journey","sortName":"game master's journey","url":"http://www.starwalkerstudios.com/gamemastersjourney","level":"Link","image":"jpg","networks":[],"categories":["Podcast"],"random":0.22235607891343534}
{"_id":{"$oid":"556d2b47eabc88c00a3a8b66"},"title":"Ken the DM","sortName":"ken the dm","url":"http://www.kenthedm.com/","level":"Link","image":"png","networks":[],"categories":["Blog"],"random":0.32398783857934177}
{"_id":{"$oid":"5575cdc0eabc88a10b718811"},"title":"Saving the Game","sortName":"saving the game","url":"http://stgcast.org/","level":"Link","image":"jpg","networks":[],"categories":["Blog","Podcast"],"random":0.2790140272118151}
{"_id":{"$oid":"5577771eeabc88a627718811"},"title":"Nvenom8 Designs","sortName":"nvenom8 designs","url":"http://www.shapeways.com/shops/Nvenom8","level":"Link","image":"png","networks":[],"categories":["Accessories"],"random":0.9279066594317555}
{"_id":{"$oid":"5577aa13eabc88d32a718811"},"title":"Made by Wombat","sortName":"made by wombat","url":"https://www.shapeways.com/shops/madebywombat","level":"Link","networks":[],"categories":["Accessories"],"random":0.3967377196531743}
{"_id":{"$oid":"557db09deabc88a004d6ea3e"},"title":"Going in Blind","sortName":"going in blind","url":"http://goinginblindpodcast.com/","level":"Link","image":"png","networks":[],"categories":["Podcast"],"random":0.5623292347881943}
{"_id":{"$oid":"557f0168eabc888a17d6ea3e"},"title":"Tabletop Audio","sortName":"tabletop audio","url":"http://tabletopaudio.com","level":"Link","image":"png","networks":[],"categories":["Accessories"],"random":0.4584491662681103}
{"_id":{"$oid":"557f3041eabc88131bd6ea3e"},"title":"Adventure Scents","sortName":"adventure scents","url":"http://adventurescents.com/","level":"Link","image":"jpg","networks":[],"categories":["Accessories"],"random":0.4463100917637348}
{"_id":{"$oid":"558248a3eabc88824cd6ea3e"},"title":"Relic Star Games","sortName":"relic star games","url":"http://www.relicstargames.com/","level":"Link","image":"png","networks":[],"categories":["Dev","Devs"],"random":0.9871802960988134}
{"_id":{"$oid":"558a191feabc880047484795"},"title":"Blackfall Press","sortName":"blackfall press","url":"https://www.facebook.com/BlackfallPressLLC","level":"Link","image":"jpg","networks":[],"categories":["Dev","Devs"],"random":0.6332184779457748}
{"_id":{"$oid":"558afacfeabc883b58484795"},"title":"Moonhaven Forest","sortName":"moonhaven forest","url":"https://moonhavenforest.wordpress.com/","level":"Link","image":"jpg","networks":[],"categories":["Blog"],"random":0.05941796931438148}
{"_id":{"$oid":"559172deeabc889b4a780ded"},"title":"Tribality","sortName":"tribality","url":"http://tribality.com/","level":"Link","image":"jpg","networks":[],"categories":["Blog"],"random":0.6254573129117489}
{"_id":{"$oid":"5596026eeabc88c92c780ded"},"title":"Rational Basis Media","sortName":"rational basis media","url":"http://www.rationalbasismedia.com/","level":"Link","image":"png","networks":[],"categories":["Dev","Devs"],"random":0.6062781577929854}
{"_id":{"$oid":"5599f7a9eabc88eb7b780ded"},"title":"Excalibur's Zone Gaming","sortName":"excalibur's zone gaming","url":"http://www.excaliburszone.com/","level":"Link","image":"png","networks":[],"categories":["Blog"],"random":0.2631632767152041}
{"_id":{"$oid":"55a81cdaeabc88431fec4b86"},"title":"Swordnut Radio","sortName":"swordnut radio","url":"http://www.swordnutradio.podbean.com/","level":"Link","networks":[],"categories":["Liveplay","Podcast"],"random":0.7164462360087782,"image":"jpg"}
{"_id":{"$oid":"55b1400ceabc88bd09e06f5b"},"title":"Glass Cannon Podcast","sortName":"glass cannon podcast","url":"http://www.glasscannonpodcast.com/","level":"Link","image":"png","networks":[],"categories":["Podcast","Videocast"],"random":0.9526774398982525}
{"_id":{"$oid":"55b1404beabc88da09e06f5b"},"title":"Fail Squad Games","sortName":"fail squad games","url":"failsquadgames.com","level":"Link","image":"jpg","networks":[],"categories":["Devs"],"random":0.8581457119435072}
{"_id":{"$oid":"55b140d5eabc889d09e06f5b"},"title":"The Art Goblin's Dungeon","sortName":"the art goblin's dungeon","url":"http://www.lmetcalf.com/","level":"Link","image":"jpg","networks":[],"categories":["Accessories"],"random":0.7188471059780568}
{"_id":{"$oid":"55b14104eabc880b0ae06f5b"},"title":"BLOOD: Path of the Shinobi","sortName":"blood: path of the shinobi","url":"http://lettuceinngames.wix.com/blood","level":"Link","image":"jpg","networks":[],"categories":["Devs"],"random":0.009611597983166575}
{"_id":{"$oid":"55b14142eabc88210ae06f5b"},"title":"Epic Gaming Party","sortName":"epic gaming party","url":"http://www.twitch.tv/epicgamingparty","level":"Link","image":"jpg","networks":[],"categories":["Liveplay"],"random":0.6503959463443607}
{"_id":{"$oid":"55b1ab33eabc88e713e06f5b"},"title":"Crit Juice","sortName":"crit juice","url":"http://www.critjuice.com/","level":"Link","image":"jpg","networks":[],"categories":["Liveplay","Videocast"],"random":0.06930698710493743}
{"_id":{"$oid":"55b4488eeabc887b41e06f5b"},"title":"Numenera Journal","sortName":"numenera journal","url":"http://www.numenerajournals.com/","level":"Link","networks":[],"categories":["Blog"],"random":0.05984864174388349}
{"_id":{"$oid":"55b44903eabc88c041e06f5b"},"title":"Shianra","sortName":"shianra","url":"http://shianra.com/","level":"Link","image":"jpg","networks":[],"categories":["Blog"],"random":0.5190925593487918}
{"_id":{"$oid":"55b7d559eabc88950d65502f"},"title":"Elderwood Boxes","sortName":"elderwood boxes","url":"https://elderwoodboxes.com/","level":"Link","image":"jpg","networks":[],"categories":["Accessories"],"random":0.10912246070802212}
{"_id":{"$oid":"55ba5fc0eabc88043f65502f"},"title":"Fablestone Dice","sortName":"fablestone dice","url":"http://www.fablestonedice.com/","level":"Link","image":"jpg","networks":[],"categories":["Accessories"],"random":0.2864265260286629}
{"_id":{"$oid":"55c96062eabc88b472e9104a"},"title":"TheWorstDM","sortName":"theworstdm","url":"http://theworstdm.com/","level":"Link","image":"jpg","networks":[],"categories":["Blog"],"random":0.22747759870253503}
{"_id":{"$oid":"55d09f97eabc88a67de9104a"},"title":"MFG Cast","sortName":"mfg cast","url":"http://www.mfgcast.com/","level":"Link","image":"jpg","networks":[],"categories":["Blog","Podcast"],"random":0.9950003528501838}
{"_id":{"$oid":"55d0a043eabc88bf7de9104a"},"title":"ARMR Studios","sortName":"armr studios","url":"https://armrstudios.wordpress.com/","level":"Link","image":"jpg","networks":[],"categories":["Devs"],"random":0.46119479299522936}
{"_id":{"$oid":"561adac5eabc88d040cc3dc5"},"title":"The CO-OP Couch","sortName":"the co-op couch","url":"http://thecoopcouch.podbean.com/","level":"Link","networks":[],"categories":["Podcast"],"random":0.6405485433060676,"image":"jpg"}
{"_id":{"$oid":"561affcaeabc883444cc3dc5"},"title":"DnD Dice","sortName":"dnd dice","url":"http://www.dnddice.com/","level":"Link","image":"jpg","networks":[],"categories":["Accessories"],"random":0.7695049340836704}
{"_id":{"$oid":"561b0265eabc889244cc3dc5"},"title":"How We Roll","sortName":"how we roll","url":"http://www.howwerollpodcast.com/","level":"Link","image":"jpg","networks":[],"categories":["Podcast"],"random":0.17093566711992025}
{"_id":{"$oid":"561b0564eabc880745cc3dc5"},"title":"Little CLUUs","sortName":"little cluus","url":"https://www.etsy.com/shop/LittleCLUUs","level":"Link","image":"jpg","networks":[],"categories":["Accessories"],"random":0.6658187804277986}
{"_id":{"$oid":"5621de43eabc88951e8b4567"},"title":"The Dread Gazebo","sortName":"the dread gazebo","url":"http://dreadgazebo.net/","level":"Link","image":"jpg","networks":[],"categories":["Blog"],"random":0.7272401549853384}
{"_id":{"$oid":"56299c3deabc88a15405ab76"},"title":"AKO Dice","sortName":"ako dice","url":"http://www.ako-dice.com/","level":"Link","image":"png","networks":[],"categories":["Accessories"],"random":0.9372128767427057}
{"_id":{"$oid":"562c16b4eabc88911105ab76"},"title":"The Rolistes","sortName":"the rolistes","url":"https://rolistespod.wordpress.com/","level":"Link","image":"jpg","networks":[],"categories":["Podcast"],"random":0.75590855977498}
{"_id":{"$oid":"566714ebeabc88f708f72cc6"},"title":"Iron Crown Games","sortName":"iron crown games","url":"http://ironcrown.com/","level":"Link","image":"jpg","networks":[],"categories":["Devs"],"random":0.049128614366054535}
{"_id":{"$oid":"5669aa96eabc88d64af72cc6"},"title":"Easy Dice Roller Co.","sortName":"easy dice roller co.","url":"http://easyrollerdice.com/","level":null,"image":"jpg","networks":[],"categories":["Accessories"],"random":0.42996234353631735}
{"_id":{"$oid":"5669aadfeabc880c4af72cc6"},"title":"Campaign Mastery","sortName":"campaign mastery","url":"http://www.campaignmastery.com/","level":"Link","networks":[],"categories":["Blog"],"random":0.09529725974425673,"image":"jpg"}
{"_id":{"$oid":"5682bc7deabc888714f087e1"},"title":"The Polyhedron Society's Actual Play Podcast","sortName":"the polyhedron society's actual play podcast","url":"http://thepolyhedronsociety.com/podcast-2/","level":"Link","networks":[],"categories":["Podcast"],"random":0.6958000268787146,"image":"jpg"}
{"_id":{"$oid":"568bbd45eabc88b045bd8929"},"title":"Geek in the Closet","sortName":"geek in the closet","url":"http://geekinthecloset.com/GITC%20Wordpress/","level":"Link","networks":[],"categories":["Blog"],"random":0.4440957286860794,"image":"jpg"}
{"_id":{"$oid":"56971f16eabc887d20749414"},"title":"Dungeon Crate","sortName":"dungeon crate","url":"http://www.dungeoncrate.com/","level":"Link","image":"jpg","networks":[],"categories":["Accessories"],"random":0.15828970377333462}
{"_id":{"$oid":"56972c71eabc888521749414"},"title":"DnD5e Podcast","sortName":"dnd5e podcast","url":"http://www.dnd5epodcast.com/","level":"Link","image":"png","networks":[],"categories":["Podcast"],"random":0.6351286370772868}
{"_id":{"$oid":"56981caceabc883339749414"},"title":"NPC Cast","sortName":"npc cast","url":"http://npccast.com/","level":"Link","image":"jpg","networks":[],"categories":["Podcast"],"random":0.12877602176740766}
{"_id":{"$oid":"5698e656eabc88e948749414"},"title":"Misdirected Mark","sortName":"misdirected mark","url":"http://misdirectedmark.com/","level":"Link","image":"jpg","networks":[],"categories":["Blog","Podcast"],"random":0.8845003845635802}
{"_id":{"$oid":"5698e6b9eabc88f248749414"},"title":"Too Cool For Tabletop","sortName":"too cool for tabletop","url":"http://www.toocoolfortabletop.com/","level":"Link","networks":[],"categories":["Podcast"],"random":0.761713893385604}
{"_id":{"$oid":"569ef58beabc88ff68f43aa6"},"title":"Legends of Tabletop","sortName":"legends of tabletop","url":"http://www.legendsoftabletop.com/","level":"Link","image":"png","networks":[],"categories":["Podcast"],"random":0.304313124390319}
{"_id":{"$oid":"56a3c439eabc887273f43aa6"},"title":"Runkle Plays Games","sortName":"runkle plays games","url":"http://runkleplaysgames.com/","level":"Link","image":"jpg","networks":[],"categories":["Blog"],"random":0.06382062914781272}
{"_id":{"$oid":"56ac0e3beabc88f063b4198c"},"title":"Dungeon Masters Block","sortName":"dungeon masters block","url":"http://dungeonmasterblock.podbean.com/","level":"Link","image":"jpg","networks":[],"categories":["Podcast"],"random":0.9396756566129625}
{"_id":{"$oid":"56b52c22eabc88ec720d99ef"},"title":"Emerald Samurai","sortName":"emerald samurai","url":"http://emeraldsamurai.com/","level":"Link","image":"jpg","networks":[],"categories":["Blog","Accessories"],"random":0.31576527561992407}
{"_id":{"$oid":"56b61056eabc881f0f0d99ef"},"title":"Super Secret Rebel Base","sortName":"super secret rebel base","url":"http://www.supersecretrebelbase.com/","level":"Link","image":"png","networks":[],"categories":["Podcast"],"random":0.6043876449111849}
{"_id":{"$oid":"56d08248eabc88e138584705"},"title":"Tales of a GM","sortName":"tales of a gm","url":"http://talesofagm.com/","level":"Link","image":"png","networks":[],"categories":["Blog"],"random":0.3470796369947493}
{"_id":{"$oid":"56d08eb3eabc88223b584705"},"title":"Openly Gamer Theatre","sortName":"openly gamer theatre","url":"http://openlygamer.com/","level":"Link","image":"jpg","networks":["rpga"],"categories":["Blog"],"random":0.24054996552877128}
{"_id":{"$oid":"56d1c560eabc88fd55584705"},"title":"Mythic Makings","sortName":"mythic makings","url":"http://www.mythicmakings.com/","level":"Link","image":"jpg","networks":[],"categories":["Accessories"],"random":0.22994899237528443}
{"_id":{"$oid":"56d4de82eabc881043df3577"},"title":"Modifier Podcast","sortName":"modifier podcast","url":"http://modifierpodcast.tumblr.com/","level":"Link","image":"png","networks":[],"categories":["Blog","Podcast"],"random":0.9055908904410899}
{"_id":{"$oid":"56d6df69eabc882403df3577"},"title":"Heavy Metal GM","sortName":"heavy metal gm","url":"https://heavymetalgm.wordpress.com/","level":"Link","image":"jpg","networks":[],"categories":["Blog"],"random":0.79080676776357}
{"_id":{"$oid":"56db789feabc88f835df3577"},"title":"Plate Mail Games","sortName":"plate mail games","url":"http://www.drivethrurpg.com/browse/pub/4847/Plate-Mail-Games?affiliate_id=739399","level":"Link","image":"jpg","networks":[],"categories":["Accessories"],"random":0.8240373025182635}
{"_id":{"$oid":"56ddb02eeabc88e9318c36ab"},"title":"Tiny Tokens - Gaming Accessories","sortName":"tiny tokens - gaming accessories","url":"http://www.tiny-tokens.com/","level":"Link","image":"png","networks":[],"categories":["Accessories"],"random":0.9453221121802926}
{"_id":{"$oid":"56e01e26eabc88470e8c36ab"},"title":"Knife's Edge Games","sortName":"knife's edge games","url":"https://knifesedgepbp.wordpress.com/","level":"Link","image":"jpg","networks":[],"categories":["Blog"],"random":0.11044856067746878}
{"_id":{"$oid":"56e94db6eabc883d35cd5ca7"},"title":"Mike's RPG Toolbox","sortName":"mike's rpg toolbox","url":"http://mikesrpgtoolbox.com/","level":"Link","image":"png","networks":[],"categories":["Blog"],"random":0.9411461493000388}
{"_id":{"$oid":"570c6306eabc884c3f4460c2"},"title":"Hero Forge","sortName":"hero forge","url":"https://www.heroforge.com/","level":"Link","image":"jpg","networks":[],"categories":["Accessories"],"random":0.0030903040897101164}
{"_id":{"$oid":"5710f5c9eabc88fd274460c2"},"title":"Dice Stormers","sortName":"dice stormers","url":"http://dicestorm.com/","level":"Link","image":"jpg","networks":[],"categories":["Podcast","Liveplay"],"random":0.2549725132994354}
{"_id":{"$oid":"5714dccceabc88e727aa3a1b"},"title":"Shane Plays Radio","sortName":"shane plays radio","url":"http://shaneplays.com/","level":"Link","image":"png","networks":[],"categories":["Podcast"],"random":0.2581568812020123}
{"_id":{"$oid":"5749fcf8eabc88c6305245b9"},"title":"Swallows of the South","sortName":"swallows of the south","url":"https://swallowsofthesouth.com/","level":"Link","image":"jpg","networks":["rpga"],"categories":["Podcast"],"random":0.3359408292453736}
{"_id":{"$oid":"574b8708eabc887b6a5245b9"},"title":"City of Brass","sortName":"city of brass","url":"https://www.cityofbrass.io/","level":"Link","image":"png","networks":["rpga"],"categories":["Accessories"],"random":0.5128737846389413}
{"_id":{"$oid":"5776ff01eabc889c1479f765"},"title":"Virtual Play","sortName":"virtual play","url":"http://virtualplay.libsyn.com/","level":"Link","networks":[],"categories":["Podcast"],"random":0.6528600584715605}
{"_id":{"$oid":"578cecaeeabc884a63d2aeb8"},"title":"Dungeons and Distractions","sortName":"dungeons and distractions","url":"http://dungeonsanddistractions.podbean.com/","level":"Link","image":"jpg","networks":[],"categories":["Podcast"],"random":0.23877419042401016}
{"_id":{"$oid":"578ceccdeabc886663d2aeb8"},"title":"The Distractions Podcast","sortName":"the distractions podcast","url":"http://thedistractionspodcast.podbean.com/","level":"Link","image":"jpg","networks":[],"categories":["Podcast"],"random":0.803909586276859}
{"_id":{"$oid":"578cecf4eabc88a063d2aeb8"},"title":"Distractions Media","sortName":"distractions media","url":"http://www.distractionsmedia.com/","level":"Link","networks":[],"categories":["Podcast"],"random":0.1077477945946157,"image":"jpg"}
{"_id":{"$oid":"578ea7cbeabc88b272d2aeb8"},"title":"Fate of Heroes","sortName":"fate of heroes","url":"http://fateofheroes.podbean.com/","level":"Link","image":"png","networks":[],"categories":["Podcast"],"random":0.6594378547742963}
{"_id":{"$oid":"579a2f88eabc88fa27847f79"},"title":"Drawlab Entertainment","sortName":"drawlab entertainment","url":"http://www.drawlab.com/","level":"Link","image":"jpg","networks":[],"categories":["Accessories"],"random":0.3077452965080738}
